esmond_client/__init__.py
esmond_client/jmx.py
esmond_client/snmp.py
esmond_client/timeseries.py
esmond_client/util.py
esmond_client/perfsonar/__init__.py
esmond_client/perfsonar/post.py
esmond_client/perfsonar/query.py
esmond_client/perfsonar/util.py
esmond_client-4.2.1.data/scripts/esmond-ps-get
esmond_client-4.2.1.data/scripts/esmond-ps-get-bulk
esmond_client-4.2.1.data/scripts/esmond-ps-get-endpoints
esmond_client-4.2.1.data/scripts/esmond-ps-get-metadata
esmond_client-4.2.1.data/scripts/esmond-ps-load-gridftp
esmond_client-4.2.1.data/scripts/esmond-ps-pipe
esmond_client-4.2.1.dist-info/DESCRIPTION.rst
esmond_client-4.2.1.dist-info/METADATA
esmond_client-4.2.1.dist-info/RECORD
esmond_client-4.2.1.dist-info/WHEEL
esmond_client-4.2.1.dist-info/metadata.json
esmond_client-4.2.1.dist-info/top_level.txt
