Metadata-Version: 2.0
Name: esmond-client
Version: 4.2.1
Summary: API client libraries and command line tools for the ESnet Monitoring Daemon (esmond).
Home-page: http://software.es.net/esmond/
Author: Monte M. Goode
Author-email: MMGoode@lbl.gov
License: UNKNOWN
Platform: UNKNOWN
Classifier: Development Status :: 5 - Production/Stable
Classifier: Intended Audience :: Developers
Classifier: Intended Audience :: Telecommunications Industry
Classifier: Environment :: Console
Classifier: License :: OSI Approved :: BSD License
Classifier: Operating System :: POSIX
Classifier: Programming Language :: Python :: 2
Classifier: Topic :: Internet
Classifier: Topic :: System :: Networking
Classifier: Topic :: Software Development :: Libraries
Requires-Dist: python-dateutil
Requires-Dist: requests
